LICENSE
MANIFEST.in
README.rst
build-requirements.txt
requirements.txt
setup.py
test-requirements.txt
augpy/CMakeLists.txt
augpy/__init__.py
augpy/blur.cu
augpy/blur.h
augpy/core.cpp
augpy/core.h
augpy/dispatch.h
augpy/elementwise.cuh
augpy/exception.h
augpy/function.cpp
augpy/function.h
augpy/gamma.cu
augpy/gamma.h
augpy/image.py
augpy/iterator.cuh
augpy/module.cpp
augpy/numeric_limits.py
augpy/nvjpegdecoder.cpp
augpy/nvjpegdecoder.h
augpy/random.cu
augpy/random.h
augpy/reduce.cu
augpy/reduce.h
augpy/saturate_cast.cuh
augpy/tensor.cpp
augpy/tensor.h
augpy/tensor_cast.cu
augpy/tensor_cmp.cu
augpy/tensor_copy.cu
augpy/tensor_math.cu
augpy/translate_idx.cuh
augpy/warp_affine.cu
augpy/warp_affine.h
augpy.egg-info/PKG-INFO
augpy.egg-info/SOURCES.txt
augpy.egg-info/dependency_links.txt
augpy.egg-info/not-zip-safe
augpy.egg-info/requires.txt
augpy.egg-info/top_level.txt
augpy/cnmem/CMakeLists.txt
augpy/cnmem/LICENSE
augpy/cnmem/README.md
augpy/cnmem/include/cnmem.h
augpy/cnmem/src/cnmem.cpp
augpy/cnmem/tests/cnmem_kernel_test.cu
augpy/cnmem/tests/cnmem_tests.cpp
augpy/cub/LICENSE.TXT
augpy/cub/README.md
augpy/cub/cub/cub.cuh
augpy/cub/cub/util_allocator.cuh
augpy/cub/cub/util_arch.cuh
augpy/cub/cub/util_debug.cuh
augpy/cub/cub/util_device.cuh
augpy/cub/cub/util_macro.cuh
augpy/cub/cub/util_namespace.cuh
augpy/cub/cub/util_ptx.cuh
augpy/cub/cub/util_type.cuh
augpy/cub/cub/agent/agent_histogram.cuh
augpy/cub/cub/agent/agent_radix_sort_downsweep.cuh
augpy/cub/cub/agent/agent_radix_sort_upsweep.cuh
augpy/cub/cub/agent/agent_reduce.cuh
augpy/cub/cub/agent/agent_reduce_by_key.cuh
augpy/cub/cub/agent/agent_rle.cuh
augpy/cub/cub/agent/agent_scan.cuh
augpy/cub/cub/agent/agent_segment_fixup.cuh
augpy/cub/cub/agent/agent_select_if.cuh
augpy/cub/cub/agent/agent_spmv_orig.cuh
augpy/cub/cub/agent/single_pass_scan_operators.cuh
augpy/cub/cub/block/block_adjacent_difference.cuh
augpy/cub/cub/block/block_discontinuity.cuh
augpy/cub/cub/block/block_exchange.cuh
augpy/cub/cub/block/block_histogram.cuh
augpy/cub/cub/block/block_load.cuh
augpy/cub/cub/block/block_radix_rank.cuh
augpy/cub/cub/block/block_radix_sort.cuh
