Metadata-Version: 2.1
Name: augpy
Version: 1.0.0a1
Summary: Lightweight CUDA tensor functions with a focus on image data augmentation.
Home-page: UNKNOWN
Author: Joachim Folz
Author-email: joachim.folz@dfki.de
License: MIT
Project-URL: Documentation, https://gitlab.com/jfolz/augpy/blob/master/README.rst
Project-URL: Source, https://gitlab.com/jfolz/augpy
Project-URL: Tracker, https://gitlab.com/jfolz/augpy/issues
Keywords: CUDA tensor math data augmentation image affine warp transform gaussian blur gamma correction
Platform: UNKNOWN
Classifier: Development Status :: 3 - Alpha
Classifier: Intended Audience :: Science/Research
Classifier: Programming Language :: Python :: 3.6
Classifier: Programming Language :: Python :: 3.7
Classifier: Programming Language :: Python :: 3.8
Classifier: License :: OSI Approved :: MIT License
